CHANGELOG.txt
LICENCE.txt
README.txt
setup.py
javalikearrays/__init__.py
javalikearrays/test.py
javalikearrays.egg-info/PKG-INFO
javalikearrays.egg-info/SOURCES.txt
javalikearrays.egg-info/dependency_links.txt
javalikearrays.egg-info/top_level.txt